doipclient/__init__.py
doipclient/client.py
doipclient/connectors.py
doipclient/constants.py
doipclient/messages.py
doipclient/py.typed
doipclient-1.1.8.dist-info/licenses/LICENSE
doipclient-1.1.8.dist-info/METADATA
doipclient-1.1.8.dist-info/WHEEL
doipclient-1.1.8.dist-info/top_level.txt
doipclient-1.1.8.dist-info/RECORD
